{
	"class" : {
		"clearFilterAutomatically" : "LS 7/12/2018 11:53",
		"clearFilterAutomatically:" : "CG 7/11/2018 18:03",
		"on:list:selected:changeSelected:menu:keystroke:" : "LS 7/12/2018 13:30",
		"toolIconsToMaterialIcons" : "Max 7/25/2018 13:57" },
	"instance" : {
		"autoDeselect" : "CG 7/11/2018 17:39",
		"autoDeselect:" : "CG 7/11/2018 17:39",
		"basicKeyPressed:" : "CG 7/11/2018 17:40",
		"changeSelected" : "CG 7/11/2018 17:40",
		"changeSelected:" : "CG 7/11/2018 17:40",
		"changed" : "mats 7/9/2018 15:07",
		"checkForChangedContent" : "Max 7/25/2018 10:52",
		"clearFilterAutomatically" : "CG 7/11/2018 17:40",
		"clearFilterAutomatically:" : "CG 7/11/2018 17:40",
		"commandKeyTypedIntoMenu:" : "mats 7/9/2018 15:31",
		"doubleClick:" : "JW 7/25/2018 14:20",
		"doubleClickSelector" : "CG 7/11/2018 17:41",
		"doubleClickSelector:" : "CG 7/11/2018 17:41",
		"filterableList" : "mats 7/9/2018 16:51",
		"getCurrentSelectionIndex" : "CG 7/11/2018 17:41",
		"getHelpSelector" : "CG 7/11/2018 17:41",
		"getHelpSelector:" : "CG 7/11/2018 17:41",
		"getIconSelector" : "CG 7/11/2018 17:41",
		"getIconSelector:" : "CG 7/11/2018 17:41",
		"getListElementSelector" : "CG 7/11/2018 17:41",
		"getListElementSelector:" : "CG 7/11/2018 17:42",
		"getListSelector" : "CG 7/11/2018 17:42",
		"getListSelector:" : "CG 7/11/2018 17:42",
		"getListSize" : "CG 7/11/2018 17:42",
		"getListSizeSelector" : "CG 7/11/2018 17:42",
		"getListSizeSelector:" : "CG 7/11/2018 17:42",
		"getMaterialIconFrom:" : "mats 7/10/2018 14:06",
		"getMenu:" : "Max 7/25/2018 10:59",
		"getMenuTitleSelector" : "CG 7/11/2018 17:43",
		"getMenuTitleSelector:" : "CG 7/11/2018 17:43",
		"handleBasicKeys:" : "CG 7/11/2018 17:43",
		"handlesBasicKeys" : "CG 7/11/2018 17:43",
		"handlesKeyboard:" : "CG 7/11/2018 17:44",
		"initForKeystrokes" : "CG 7/11/2018 17:44",
		"initialize" : "mats 7/10/2018 12:49",
		"keyStroke:" : "mats 7/9/2018 15:24",
		"keyboardFocusChange:" : "CG 7/11/2018 17:44",
		"keystrokeActionSelector" : "mats 7/10/2018 13:01",
		"keystrokeActionSelector:" : "mats 7/9/2018 15:31",
		"keystrokePreviewSelector" : "CG 7/11/2018 17:45",
		"keystrokePreviewSelector:" : "mats 7/9/2018 15:31",
		"lastKeystrokeTime" : "CG 7/11/2018 17:45",
		"lastKeystrokeTime:" : "CG 7/11/2018 17:45",
		"listCollection" : "CG 7/11/2018 17:55",
		"listCollection:" : "CG 7/11/2018 17:55",
		"maximumSelection" : "mats 7/10/2018 11:33",
		"menu" : "CG 7/11/2018 17:55",
		"menu:" : "CG 7/11/2018 17:55",
		"model" : "CG 7/11/2018 17:55",
		"model:" : "mats 7/10/2018 11:07",
		"modelSelect:" : "JW 7/25/2018 14:29",
		"modifierKeyPressed:" : "CG 7/11/2018 17:56",
		"mouseDown:" : "JW 7/25/2018 14:25",
		"mouseEnter:" : "LS 7/12/2018 11:45",
		"mouseEnterDragging:" : "JW 7/25/2018 14:29",
		"mouseLeave:" : "LS 7/12/2018 11:37",
		"mouseLeaveDragging:" : "JW 7/25/2018 11:06",
		"mouseMove:" : "JW 7/25/2018 11:12",
		"numSelectionsInView" : "mats 7/10/2018 11:33",
		"potentialDropRow" : "CG 7/11/2018 17:57",
		"previewKeystroke:" : "CG 7/11/2018 17:57",
		"priorSelection" : "CG 7/11/2018 17:57",
		"priorSelection:" : "CG 7/11/2018 17:57",
		"resetPotentialDropRow" : "CG 7/11/2018 17:57",
		"rowAtLocation:" : "JW 7/6/2018 16:58",
		"selectListItem:" : "JW 7/25/2018 14:27",
		"selected" : "CG 7/11/2018 17:58",
		"selected:" : "CG 7/11/2018 17:58",
		"selection" : "JW 7/9/2018 23:29",
		"selectionIndex" : "JW 7/19/2018 12:29",
		"specialKeyPressed:" : "LS 7/12/2018 13:27",
		"update:" : "mats 7/10/2018 14:00",
		"updateList" : "mats 7/10/2018 13:54",
		"updateListMorphs" : "mats 7/3/2018 14:57",
		"wantsKeyboardFocus" : "mats 7/9/2018 16:45",
		"yellowButtonActivity:" : "CG 7/11/2018 18:00" } }
