{
	"class" : {
		"alwaysUppercase" : "JW 6/8/2018 16:09",
		"backgroundColorSelected" : "mats 7/3/2018 14:43",
		"checkToggled" : "mats 7/3/2018 13:02",
		"defaultAvatarPadding" : "mats 6/5/2018 09:09",
		"defaultBorderRadius" : "LS 6/28/2018 20:47",
		"defaultHeight" : "mats 6/4/2018 17:03",
		"defaultIconPadding" : "mats 6/5/2018 08:26",
		"defaultTextPadding" : "mats 6/5/2018 09:11",
		"denseHeight" : "mats 7/10/2018 12:43",
		"newOnList:" : "mats 5/30/2018 11:58",
		"textColorSelected" : "mats 7/3/2018 14:43" },
	"instance" : {
		"calculateColor" : "mats 7/3/2018 14:51",
		"calculateWidthByText" : "CG 7/1/2018 11:40",
		"changed" : "mats 6/1/2018 15:11",
		"checkToggled" : "mats 7/3/2018 14:44",
		"containsPoint:" : "mats 6/28/2018 00:15",
		"defaultHeight" : "mats 7/10/2018 12:53",
		"denseLayout:" : "mats 7/10/2018 12:57",
		"deselect" : "mats 7/3/2018 14:46",
		"formCache" : "mats 6/8/2018 15:32",
		"formCache:" : "mats 6/8/2018 15:32",
		"hasDenseLayout" : "mats 7/10/2018 12:47",
		"initialize" : "mats 7/9/2018 22:45",
		"isSelected" : "mats 7/3/2018 14:40",
		"labelBounds" : "LS 6/28/2018 15:25",
		"labelPositionIconNotPresent" : "mats 6/19/2018 12:30",
		"list" : "mats 6/8/2018 15:32",
		"list:" : "mats 6/8/2018 15:32",
		"mouseUp:" : "mats 6/28/2018 00:12",
		"select" : "mats 7/3/2018 14:52",
		"selected:" : "mats 7/3/2018 14:52",
		"textColor:" : "mats 6/8/2018 15:33",
		"updateFormCache" : "mats 7/3/2018 14:41",
		"updateFormCache:" : "LS 6/28/2018 21:32" } }
